{
  "studentId": "bart24",
  "score": 105,
  "maxScore": 140,
  "feedback": [
    "team\\index.html: Avoid base64 images — use image files instead.",
    "team\\index.html: Avoid base64 images — use image files instead.",
    "team\\index.html: Avoid base64 images — use image files instead.",
    "team\\index.html: Avoid base64 images — use image files instead.",
    "team\\index.html: Avoid base64 images — use image files instead.",
    "team\\index.html: Avoid base64 images — use image files instead.",
    "team\\index.html: Avoid base64 images — use image files instead.",
    "team\\index.html: Avoid base64 images — use image files instead.",
    "team\\index.html: Avoid base64 images — use image files instead.",
    "team\\index.html: Avoid base64 images — use image files instead.",
    "team\\index.html: Avoid base64 images — use image files instead.",
    "index.html: Avoid including index.html in URLs (index.html).",
    "index.html: Avoid including index.html in URLs (index.html).",
    "index.html: Avoid including index.html in URLs (team/index.html).",
    "index.html: Avoid including index.html in URLs (akademie/index.html).",
    "index.html: Avoid including index.html in URLs (zapasy/index.html).",
    "index.html: Avoid including index.html in URLs (tabulka/index.html).",
    "index.html: Avoid including index.html in URLs (kontakt/index.html).",
    "index.html: Avoid including index.html in URLs (zapasy/index.html).",
    "index.html: Avoid including index.html in URLs (tabulka/index.html).",
    "index.html: Avoid including index.html in URLs (zapasy/index.html).",
    "index.html: Avoid including index.html in URLs (kontakt/index.html).",
    "zapasy\\index.html: Avoid including index.html in URLs (../index.html).",
    "zapasy\\index.html: Avoid including index.html in URLs (../index.html).",
    "zapasy\\index.html: Avoid including index.html in URLs (../team/index.html).",
    "zapasy\\index.html: Avoid including index.html in URLs (../akademie/index.html).",
    "zapasy\\index.html: Avoid including index.html in URLs (index.html).",
    "zapasy\\index.html: Avoid including index.html in URLs (../tabulka/index.html).",
    "zapasy\\index.html: Avoid including index.html in URLs (../kontakt/index.html).",
    "team\\index.html: Avoid including index.html in URLs (../index.html).",
    "team\\index.html: Avoid including index.html in URLs (../index.html).",
    "team\\index.html: Avoid including index.html in URLs (index.html).",
    "team\\index.html: Avoid including index.html in URLs (../akademie/index.html).",
    "team\\index.html: Avoid including index.html in URLs (../zapasy/index.html).",
    "team\\index.html: Avoid including index.html in URLs (../tabulka/index.html).",
    "team\\index.html: Avoid including index.html in URLs (../kontakt/index.html).",
    "tabulka\\index.html: Avoid including index.html in URLs (../index.html).",
    "tabulka\\index.html: Avoid including index.html in URLs (../index.html).",
    "tabulka\\index.html: Avoid including index.html in URLs (../team/index.html).",
    "tabulka\\index.html: Avoid including index.html in URLs (../akademie/index.html).",
    "tabulka\\index.html: Avoid including index.html in URLs (../zapasy/index.html).",
    "tabulka\\index.html: Avoid including index.html in URLs (index.html).",
    "tabulka\\index.html: Avoid including index.html in URLs (../kontakt/index.html).",
    "kontakt\\index.html: Avoid including index.html in URLs (../index.html).",
    "kontakt\\index.html: Avoid including index.html in URLs (../index.html).",
    "kontakt\\index.html: Avoid including index.html in URLs (../team/index.html).",
    "kontakt\\index.html: Avoid including index.html in URLs (../akademie/index.html).",
    "kontakt\\index.html: Avoid including index.html in URLs (../zapasy/index.html).",
    "kontakt\\index.html: Avoid including index.html in URLs (../tabulka/index.html).",
    "kontakt\\index.html: Avoid including index.html in URLs (index.html).",
    "akademie\\index.html: Avoid including index.html in URLs (../index.html).",
    "akademie\\index.html: Avoid including index.html in URLs (../index.html).",
    "akademie\\index.html: Avoid including index.html in URLs (../team/index.html).",
    "akademie\\index.html: Avoid including index.html in URLs (index.html).",
    "akademie\\index.html: Avoid including index.html in URLs (../zapasy/index.html).",
    "akademie\\index.html: Avoid including index.html in URLs (../tabulka/index.html).",
    "akademie\\index.html: Avoid including index.html in URLs (../kontakt/index.html).",
    "Include at least one phone link using tel:.",
    "index.html: External link should open in new tab.",
    "index.html: External link should open in new tab.",
    "zapasy\\index.html: External link should open in new tab.",
    "zapasy\\index.html: External link should open in new tab.",
    "team\\index.html: External link should open in new tab.",
    "team\\index.html: External link should open in new tab.",
    "tabulka\\index.html: External link should open in new tab.",
    "tabulka\\index.html: External link should open in new tab.",
    "kontakt\\index.html: External link should open in new tab.",
    "kontakt\\index.html: External link should open in new tab.",
    "akademie\\index.html: External link should open in new tab.",
    "akademie\\index.html: External link should open in new tab."
  ],
  "breakdown": {
    "Site Size": {
      "name": "Site Size",
      "score": 10,
      "maxScore": 10,
      "feedback": []
    },
    "Performance: Images": {
      "name": "Performance: Images",
      "score": 10,
      "maxScore": 10,
      "feedback": []
    },
    "Performance: Data URLs": {
      "name": "Performance: Data URLs",
      "score": 0,
      "maxScore": 10,
      "feedback": [
        "team\\index.html: Avoid base64 images — use image files instead.",
        "team\\index.html: Avoid base64 images — use image files instead.",
        "team\\index.html: Avoid base64 images — use image files instead.",
        "team\\index.html: Avoid base64 images — use image files instead.",
        "team\\index.html: Avoid base64 images — use image files instead.",
        "team\\index.html: Avoid base64 images — use image files instead.",
        "team\\index.html: Avoid base64 images — use image files instead.",
        "team\\index.html: Avoid base64 images — use image files instead.",
        "team\\index.html: Avoid base64 images — use image files instead.",
        "team\\index.html: Avoid base64 images — use image files instead.",
        "team\\index.html: Avoid base64 images — use image files instead."
      ]
    },
    "Maintainability: CSS Duplication": {
      "name": "Maintainability: CSS Duplication",
      "score": 15,
      "maxScore": 15,
      "feedback": []
    },
    "Maintainability: Structure": {
      "name": "Maintainability: Structure",
      "score": 10,
      "maxScore": 10,
      "feedback": []
    },
    "Accessibility: URLs": {
      "name": "Accessibility: URLs",
      "score": 0,
      "maxScore": 10,
      "feedback": [
        "index.html: Avoid including index.html in URLs (index.html).",
        "index.html: Avoid including index.html in URLs (index.html).",
        "index.html: Avoid including index.html in URLs (team/index.html).",
        "index.html: Avoid including index.html in URLs (akademie/index.html).",
        "index.html: Avoid including index.html in URLs (zapasy/index.html).",
        "index.html: Avoid including index.html in URLs (tabulka/index.html).",
        "index.html: Avoid including index.html in URLs (kontakt/index.html).",
        "index.html: Avoid including index.html in URLs (zapasy/index.html).",
        "index.html: Avoid including index.html in URLs (tabulka/index.html).",
        "index.html: Avoid including index.html in URLs (zapasy/index.html).",
        "index.html: Avoid including index.html in URLs (kontakt/index.html).",
        "zapasy\\index.html: Avoid including index.html in URLs (../index.html).",
        "zapasy\\index.html: Avoid including index.html in URLs (../index.html).",
        "zapasy\\index.html: Avoid including index.html in URLs (../team/index.html).",
        "zapasy\\index.html: Avoid including index.html in URLs (../akademie/index.html).",
        "zapasy\\index.html: Avoid including index.html in URLs (index.html).",
        "zapasy\\index.html: Avoid including index.html in URLs (../tabulka/index.html).",
        "zapasy\\index.html: Avoid including index.html in URLs (../kontakt/index.html).",
        "team\\index.html: Avoid including index.html in URLs (../index.html).",
        "team\\index.html: Avoid including index.html in URLs (../index.html).",
        "team\\index.html: Avoid including index.html in URLs (index.html).",
        "team\\index.html: Avoid including index.html in URLs (../akademie/index.html).",
        "team\\index.html: Avoid including index.html in URLs (../zapasy/index.html).",
        "team\\index.html: Avoid including index.html in URLs (../tabulka/index.html).",
        "team\\index.html: Avoid including index.html in URLs (../kontakt/index.html).",
        "tabulka\\index.html: Avoid including index.html in URLs (../index.html).",
        "tabulka\\index.html: Avoid including index.html in URLs (../index.html).",
        "tabulka\\index.html: Avoid including index.html in URLs (../team/index.html).",
        "tabulka\\index.html: Avoid including index.html in URLs (../akademie/index.html).",
        "tabulka\\index.html: Avoid including index.html in URLs (../zapasy/index.html).",
        "tabulka\\index.html: Avoid including index.html in URLs (index.html).",
        "tabulka\\index.html: Avoid including index.html in URLs (../kontakt/index.html).",
        "kontakt\\index.html: Avoid including index.html in URLs (../index.html).",
        "kontakt\\index.html: Avoid including index.html in URLs (../index.html).",
        "kontakt\\index.html: Avoid including index.html in URLs (../team/index.html).",
        "kontakt\\index.html: Avoid including index.html in URLs (../akademie/index.html).",
        "kontakt\\index.html: Avoid including index.html in URLs (../zapasy/index.html).",
        "kontakt\\index.html: Avoid including index.html in URLs (../tabulka/index.html).",
        "kontakt\\index.html: Avoid including index.html in URLs (index.html).",
        "akademie\\index.html: Avoid including index.html in URLs (../index.html).",
        "akademie\\index.html: Avoid including index.html in URLs (../index.html).",
        "akademie\\index.html: Avoid including index.html in URLs (../team/index.html).",
        "akademie\\index.html: Avoid including index.html in URLs (index.html).",
        "akademie\\index.html: Avoid including index.html in URLs (../zapasy/index.html).",
        "akademie\\index.html: Avoid including index.html in URLs (../tabulka/index.html).",
        "akademie\\index.html: Avoid including index.html in URLs (../kontakt/index.html)."
      ]
    },
    "Accessibility: Favicon": {
      "name": "Accessibility: Favicon",
      "score": 10,
      "maxScore": 10,
      "feedback": []
    },
    "Accessibility: Contact Links": {
      "name": "Accessibility: Contact Links",
      "score": 5,
      "maxScore": 10,
      "feedback": [
        "Include at least one phone link using tel:."
      ]
    },
    "Accessibility: Link Behavior": {
      "name": "Accessibility: Link Behavior",
      "score": 0,
      "maxScore": 10,
      "feedback": [
        "index.html: External link should open in new tab.",
        "index.html: External link should open in new tab.",
        "zapasy\\index.html: External link should open in new tab.",
        "zapasy\\index.html: External link should open in new tab.",
        "team\\index.html: External link should open in new tab.",
        "team\\index.html: External link should open in new tab.",
        "tabulka\\index.html: External link should open in new tab.",
        "tabulka\\index.html: External link should open in new tab.",
        "kontakt\\index.html: External link should open in new tab.",
        "kontakt\\index.html: External link should open in new tab.",
        "akademie\\index.html: External link should open in new tab.",
        "akademie\\index.html: External link should open in new tab."
      ]
    },
    "SEO": {
      "name": "SEO",
      "score": 15,
      "maxScore": 15,
      "feedback": []
    },
    "Escaping": {
      "name": "Escaping",
      "score": 10,
      "maxScore": 10,
      "feedback": []
    },
    "Semantics (Required)": {
      "name": "Semantics (Required)",
      "score": 20,
      "maxScore": 20,
      "feedback": []
    }
  }
}